setup.cfg
setup.py
SMPNetwork.egg-info/PKG-INFO
SMPNetwork.egg-info/SOURCES.txt
SMPNetwork.egg-info/dependency_links.txt
SMPNetwork.egg-info/requires.txt
SMPNetwork.egg-info/top_level.txt
smpnetwork/__init__.py
smpnetwork/message.py
smpnetwork/response.py
smpnetwork/server.py
smpnetwork/smp.py
smpnetwork/tools.py