Metadata-Version: 1.0
Name: SMPNetwork
Version: 0.0.3
Summary: Simple Messaging Protocol between a server and multiple clients. Supports continuous connections and SSL.
Home-page: https://github.com/halilozercan/smp
Author: Halil Ozercan
Author-email: halilozercan@gmail
License: UNKNOWN
Platform: UNKNOWN
